neurograph_core/__init__.py
neurograph_core/ffi.py
neurograph_core/libneurograph_core.so
ngcore-1.0.0.dist-info/METADATA
ngcore-1.0.0.dist-info/WHEEL
ngcore-1.0.0.dist-info/RECORD
