Metadata-Version: 2.4
Name: ngcore
Version: 1.0.0
Summary: High-performance cognitive computing platform with Rust Core, WebSocket API, and real-time event processing (304K events/sec)
Keywords: cognitive-architecture,neuroscience,ai,rust,websocket
Home-Page: https://github.com/dchrnv/neurograph
Author: Chernov Denys <noreply@neurograph.dev>
Author-email: Chernov Denys <noreply@neurograph.dev>
License: AGPL-3.0
Project-URL: Homepage, https://github.com/dchrnv/neurograph
Project-URL: Documentation, https://github.com/dchrnv/neurograph/tree/main/docs
Project-URL: Source Code, https://github.com/dchrnv/neurograph
